pymaid/__init__.py
pymaid/channel.py
pymaid/connection.py
pymaid/pool.py
pymaid/apps/__init__.py
pymaid/apps/middleware.py
pymaid/apps/monitor/__init__.py
pymaid/apps/monitor/error.py
pymaid/apps/monitor/middleware.py
pymaid/apps/monitor/monitor.proto
pymaid/apps/monitor/monitor_pb2.py
pymaid/apps/monitor/service.py
pymaid/conf/__init__.py
pymaid/conf/defaults.py
pymaid/conf/settings.py
pymaid/error/__init__.py
pymaid/error/base.py
pymaid/error/rpc.py
pymaid/pb/__init__.py
pymaid/pb/controller.py
pymaid/pb/handler.py
pymaid/pb/listener.py
pymaid/pb/pymaid.proto
pymaid/pb/pymaid_pb2.py
pymaid/pb/stub.py
pymaid/utils/__init__.py
pymaid/utils/autoreload.py
pymaid/utils/core.py
pymaid/utils/functional.py
pymaid/utils/hash.py
pymaid/utils/logger.py
pymaid/utils/profiler.py
pymaid/utils/worker.py
pymaid/websocket/__init__.py
pymaid/websocket/exceptions.py
pymaid/websocket/utf8validator.py
pymaid/websocket/websocket.py
pymaid-0.3.8.post4.dist-info/METADATA
pymaid-0.3.8.post4.dist-info/RECORD
pymaid-0.3.8.post4.dist-info/WHEEL
pymaid-0.3.8.post4.dist-info/top_level.txt
