Metadata-Version: 2.1
Name: pymaid
Version: 0.3.8.post4
Summary: A rpc framework based on gevent/protobuf
Home-page: https://github.com/catstyle/pymaid
Author: Catstyle
Author-email: Catstyle.Lee@gmail.com
License: MIT
Keywords: rpc gevent protobuf
Platform: UNKNOWN
Classifier: Development Status :: 3 - Alpha
Classifier: Intended Audience :: Developers
Classifier: Topic :: Software Development :: Build Tools
Classifier: License :: OSI Approved :: MIT License
Classifier: Programming Language :: Python :: 2.7
Classifier: Programming Language :: Python :: 3.5
Classifier: Programming Language :: Python :: 3.6
Requires-Dist: gevent (==1.4.0)
Requires-Dist: protobuf (==3.6.1)
Requires-Dist: six
Requires-Dist: ujson
Requires-Dist: wsaccel
